src/CALM.py
src/CodeAnalyzer/CodeAnalyzer.py
src/CodeAnalyzer/__init__.py
src/__init__.py
calm_llm-0.1.0.dist-info/METADATA
calm_llm-0.1.0.dist-info/WHEEL
calm_llm-0.1.0.dist-info/entry_points.txt
calm_llm-0.1.0.dist-info/RECORD
